cdev/__init__.py
cdev/aws/__init__.py
cdev/aws/api.py
cdev/aws/dynamodb.py
cdev/aws/frontend.py
cdev/aws/iam.py
cdev/aws/kinesis.py
cdev/aws/lambda_function.py
cdev/aws/relational_db.py
cdev/aws/s3.py
cdev/aws/sns.py
cdev/aws/sqs.py
cdev/cli/__init__.py
cdev/cli/__main__.py
cdev/cli/logger.py
cdev/commands/__init__.py
cdev/commands/cloud_output.py
cdev/commands/deploy.py
cdev/commands/destroy.py
cdev/commands/environment.py
cdev/commands/git_safe.py
cdev/commands/git_safe_messages.py
cdev/commands/plan.py
cdev/commands/project_initializer.py
cdev/commands/project_initializer_params.py
cdev/commands/remove_resource.py
cdev/commands/run.py
cdev/commands/sync.py
cdev/constructs/__init__.py
cdev/constructs/environment.py
cdev/constructs/project.py
cdev/default/__init__.py
cdev/default/cloudmapper.py
cdev/default/components.py
cdev/default/environment.py
cdev/default/output_manager.py
cdev/default/project.py
cdev/project_templates/packages/requirements.txt
cdev/project_templates/packages/src/__init__.py
cdev/project_templates/packages/src/cdev_project.py
cdev/project_templates/packages/src/packages/__init__.py
cdev/project_templates/packages/src/packages/resources.py
cdev/project_templates/packages/src/packages/utils.py
cdev/project_templates/power_tools/src/__init__.py
cdev/project_templates/power_tools/src/cdev_project.py
cdev/project_templates/power_tools/src/examples/__init__.py
cdev/project_templates/power_tools/src/examples/config.py
cdev/project_templates/power_tools/src/examples/dataclass_example.py
cdev/project_templates/power_tools/src/examples/logging_example.py
cdev/project_templates/power_tools/src/examples/metrics_example.py
cdev/project_templates/power_tools/src/examples/middleware_example.py
cdev/project_templates/power_tools/src/examples/tracer_example.py
cdev/project_templates/quick_start/src/__init__.py
cdev/project_templates/quick_start/src/cdev_project.py
cdev/project_templates/quick_start/src/hello_world/__init__.py
cdev-0.0.31.dist-info/METADATA
cdev-0.0.31.dist-info/WHEEL
cdev-0.0.31.dist-info/top_level.txt
cdev-0.0.31.dist-info/RECORD
