Metadata-Version: 2.1
Name: cdev
Version: 0.0.31
Summary: CLI for cdev sdk
Home-page: UNKNOWN
Author: CDEV LLC
Author-email: daniel@cdevframework.com
License: Clear BSD
Platform: UNKNOWN
Requires-Python: >=3.7
Requires-Dist: aurora-data-api
Requires-Dist: boto3
Requires-Dist: networkx
Requires-Dist: Parsley
Requires-Dist: pydantic
Requires-Dist: python-json-logger
Requires-Dist: rich
Requires-Dist: sortedcontainers
Requires-Dist: watchdog
Requires-Dist: GitPython
Requires-Dist: typing-extensions
